pyams_file_views/__init__.py
pyams_file_views/include.py
pyams_file_views/doctests/README.rst
pyams_file_views/doctests/tales.rst
pyams_file_views/locales/pyams_file_views.pot
pyams_file_views/locales/fr/LC_MESSAGES/pyams_file_views.mo
pyams_file_views/locales/fr/LC_MESSAGES/pyams_file_views.po
pyams_file_views/skin/__init__.py
pyams_file_views/skin/tales.py
pyams_file_views/skin/resources/img/application-epub+zip.png
pyams_file_views/skin/resources/img/application-illustrator.png
pyams_file_views/skin/resources/img/application-javascript.png
pyams_file_views/skin/resources/img/application-msword-template.png
pyams_file_views/skin/resources/img/application-msword.png
pyams_file_views/skin/resources/img/application-octet-stream.png
pyams_file_views/skin/resources/img/application-pdf.png
pyams_file_views/skin/resources/img/application-pgp-encrypted.png
pyams_file_views/skin/resources/img/application-pgp-keys.png
pyams_file_views/skin/resources/img/application-pgp-signature.png
pyams_file_views/skin/resources/img/application-postscript.png
pyams_file_views/skin/resources/img/application-relaxng.png
pyams_file_views/skin/resources/img/application-rss+xml.png
pyams_file_views/skin/resources/img/application-rtf.png
pyams_file_views/skin/resources/img/application-sxw.png
pyams_file_views/skin/resources/img/application-vnd-google-earth-kml.png
pyams_file_views/skin/resources/img/application-vnd.iccprofile.png
pyams_file_views/skin/resources/img/application-vnd.ms-access.png
pyams_file_views/skin/resources/img/application-vnd.ms-excel.png
pyams_file_views/skin/resources/img/application-vnd.ms-powerpoint.png
pyams_file_views/skin/resources/img/application-vnd.oasis.opendocument.chart.png
pyams_file_views/skin/resources/img/application-vnd.oasis.opendocument.database.png
pyams_file_views/skin/resources/img/application-vnd.oasis.opendocument.formula-template.png
pyams_file_views/skin/resources/img/application-vnd.oasis.opendocument.formula.png
pyams_file_views-2.1.0.dist-info/LICENSE
pyams_file_views-2.1.0.dist-info/METADATA
pyams_file_views-2.1.0.dist-info/WHEEL
pyams_file_views-2.1.0.dist-info/entry_points.txt
pyams_file_views-2.1.0.dist-info/namespace_packages.txt
pyams_file_views-2.1.0.dist-info/top_level.txt
pyams_file_views-2.1.0.dist-info/RECORD
