Metadata-Version: 2.1
Name: pyams-file-views
Version: 2.1.0
Summary: Pyramid views for PyAMS_file package
Home-page: https://pyams.readthedocs.io
Author: Thierry Florac
Author-email: tflorac@ulthar.net
License: ZPL
Keywords: Pyramid PyAMS
Classifier: License :: OSI Approved :: Zope Public License
Classifier: Development Status :: 4 - Beta
Classifier: Programming Language :: Python
Classifier: Framework :: Pyramid
Classifier: Topic :: Software Development :: Libraries :: Python Modules
License-File: LICENSE
Requires-Dist: setuptools
Requires-Dist: fanstatic
Requires-Dist: myams-js >=1.14.0
Requires-Dist: pyams-file
Requires-Dist: pyams-form
Requires-Dist: pyams-layer
Requires-Dist: pyams-pagelet
Requires-Dist: pyams-security
Requires-Dist: pyams-skin >=1.8.0
Requires-Dist: pyams-template
Requires-Dist: pyams-utils
Requires-Dist: pyams-viewlet
Requires-Dist: pyramid
Requires-Dist: transaction
Requires-Dist: zope.component
Requires-Dist: zope.dublincore
Requires-Dist: zope.interface
Requires-Dist: zope.schema
Provides-Extra: test
Requires-Dist: pyams-catalog ; extra == 'test'
Requires-Dist: pyams-site ; extra == 'test'
Requires-Dist: pyams-zmi ; extra == 'test'
Requires-Dist: pyramid-zcml ; extra == 'test'
Requires-Dist: zope.exceptions ; extra == 'test'
